simple_fpa/__init__.py
simple_fpa/calibrate.py
simple_fpa/estimators.py
simple_fpa/inference.py
simple_fpa/kernels.py
simple_fpa/model.py
simple_fpa/plots.py
simple_fpa/simulator.py
simple_fpa/data/haile_data.csv
simple_fpa-1.7.dist-info/LICENSE
simple_fpa-1.7.dist-info/METADATA
simple_fpa-1.7.dist-info/WHEEL
simple_fpa-1.7.dist-info/top_level.txt
simple_fpa-1.7.dist-info/RECORD
