Metadata-Version: 2.1
Name: simple-fpa
Version: 1.7
Summary: Simple nonparametric inference for sealed first-price auctions.
Author: Pasha Andreyanov, Grigory Franguridi
Author-email: pandreyanov@gmail.com
License: MIT
Platform: UNKNOWN
Classifier: License :: OSI Approved :: MIT License
License-File: LICENSE
Requires-Dist: numpy
Requires-Dist: scipy
Requires-Dist: pandas
